quantumscan/__init__.py
quantumscan/__main__.py
quantumscan/cli/__init__.py
quantumscan/cli/__main__.py
quantumscan/parser/__init__.py
quantumscan/parser/ast_analyzer.py
quantumscan/parser/models.py
quantumscan/parser/scanner.py
quantumscan/parser/utils.py
quantumscan/reporting/__init__.py
quantumscan/reporting/ci_comment.py
quantumscan/reporting/html.py
quantumscan/reporting/markdown.py
quantumscan/reporting/pdf.py
quantumscan/reporting/pqc_mapping.py
blackwall_quantumscan-0.1.2.dist-info/METADATA
blackwall_quantumscan-0.1.2.dist-info/WHEEL
blackwall_quantumscan-0.1.2.dist-info/entry_points.txt
blackwall_quantumscan-0.1.2.dist-info/top_level.txt
blackwall_quantumscan-0.1.2.dist-info/RECORD
