Metadata-Version: 2.4
Name: blackwall-quantumscan
Version: 0.1.2
Summary: PQC migration scanner: detect legacy crypto (RSA/ECC/SHA1/MD5) and guide replacements.
Author: QuantumScan Team
Project-URL: Homepage, https://github.com/<your-org-or-user>/quantumscan-cli
Project-URL: Issues, https://github.com/<your-org-or-user>/quantumscan-cli/issues
Keywords: post-quantum,pqc,security,scanner,cryptography
Classifier: Programming Language :: Python :: 3
Classifier: Programming Language :: Python :: 3.11
Classifier: License :: OSI Approved :: MIT License
Classifier: Operating System :: OS Independent
Classifier: Intended Audience :: Developers
Classifier: Topic :: Security
Requires-Python: >=3.11
Requires-Dist: cryptography>=42.0.0
Requires-Dist: pygments>=2.17.0
Requires-Dist: rich>=13.0.0
Requires-Dist: jinja2>=3.1.3
